[
  {
    "id": "rick_sanchez",
    "name": "Rick Sanchez",
    "author": "starriichan",
    "sprites": 46,
    "scale_recommended": 2.0,
    "climb_pad_left": 75,
    "climb_pad_right": 75,
    "thumb": "packs/rick_sanchez/thumb.png",
    "preview": "packs/rick_sanchez/preview.gif",
    "zip": "packs/rick_sanchez/pack.zip",
    "zip_subdir": "Yellow Shirt Rick"
  },
  {
    "id": "envy",
    "name": "Envy",
    "author": "rukama",
    "sprites": 52,
    "scale_recommended": 2.0,
    "climb_pad_left": 30,
    "climb_pad_right": 30,
    "thumb": "packs/envy/thumb.png",
    "preview": "packs/envy/preview.gif",
    "zip": "packs/envy/pack.zip",
    "zip_subdir": ""
  },
  {
    "id": "xela",
    "name": "Xela",
    "author": "starriichan",
    "sprites": 46,
    "scale_recommended": 2.0,
    "climb_pad_left": 45,
    "climb_pad_right": 45,
    "thumb": "packs/xela/thumb.png",
    "preview": "packs/xela/preview.gif",
    "zip": "packs/xela/pack.zip",
    "zip_subdir": ""
  },
  {
    "id": "sasori",
    "name": "Sasori",
    "author": "rukama",
    "sprites": 46,
    "scale_recommended": 2.0,
    "climb_pad_left": 50,
    "climb_pad_right": 50,
    "thumb": "packs/sasori/thumb.png",
    "preview": "packs/sasori/preview.gif",
    "zip": "packs/sasori/pack.zip",
    "zip_subdir": ""
  },
  {
    "id": "steve",
    "name": "Steve",
    "author": "unknown",
    "sprites": 48,
    "scale_recommended": 2.0,
    "climb_pad_left": 40,
    "climb_pad_right": 40,
    "thumb": "packs/steve/thumb.png",
    "zip": "packs/steve/pack.zip",
    "zip_subdir": ""
  },
  {
    "id": "ladybug",
    "name": "Marinette / Ladybug",
    "author": "kicoma",
    "sprites": 46,
    "scale_recommended": 2.0,
    "climb_pad_left": 55,
    "climb_pad_right": 55,
    "thumb": "packs/ladybug/thumb.png",
    "zip": "packs/ladybug/pack.zip",
    "zip_subdir": ""
  }
]
